tzf.pyramid_routing-0.1.2-py2.7-nspkg.pth
tests/test_routing.py
tests/__init__.py
tests/conftest.py
tests/routes_definitions/module_to_include_2.py
tests/routes_definitions/__init__.py
tests/routes_definitions/module_to_include_1.py
tests/routes_definitions/routing_to_include_2/__init__.py
tests/routes_definitions/routing/__init__.py
tests/routes_definitions/routing_two_moduled/second.py
tests/routes_definitions/routing_two_moduled/module.py
tests/routes_definitions/routing_two_moduled/__init__.py
tests/routes_definitions/routing_prefixed/second.py
tests/routes_definitions/routing_prefixed/module.py
tests/routes_definitions/routing_prefixed/__init__.py
tests/routes_definitions/routing_moduled/module.py
tests/routes_definitions/routing_moduled/__init__.py
tests/routes_definitions/routing_to_include_1/__init__.py
tzf/pyramid_routing/__init__.py
tzf.pyramid_routing-0.1.2.dist-info/top_level.txt
tzf.pyramid_routing-0.1.2.dist-info/METADATA
tzf.pyramid_routing-0.1.2.dist-info/WHEEL
tzf.pyramid_routing-0.1.2.dist-info/pydist.json
tzf.pyramid_routing-0.1.2.dist-info/RECORD
tzf.pyramid_routing-0.1.2.dist-info/DESCRIPTION.rst
tzf.pyramid_routing-0.1.2.dist-info/namespace_packages.txt
