Metadata-Version: 2.0
Name: tzf.pyramid-routing
Version: 0.1.2
Summary: Reads and sets routing configuration from a package
Home-page: https://github.com/fizyk/pyramid_routing
Author: Grzegorz Sliwinski
Author-email: username: fizyk, domain: fizyk.net.pl
License: MIT License
Keywords: pyramid routing
Platform: UNKNOWN
Classifier: Development Status :: 4 - Beta
Classifier: Environment :: Web Environment
Classifier: Intended Audience :: Developers
Classifier: License :: OSI Approved :: MIT License
Classifier: Natural Language :: English
Classifier: Operating System :: OS Independent
Classifier: Programming Language :: Python
Classifier: Programming Language :: Python :: 2.6
Classifier: Programming Language :: Python :: 2.7
Classifier: Programming Language :: Python :: 3
Classifier: Framework :: Pyramid
Classifier: Topic :: Internet :: WWW/HTTP
Classifier: Topic :: Internet :: WWW/HTTP :: WSGI
Classifier: Topic :: Software Development :: Libraries :: Python Modules
Requires-Dist: pyramid
Provides-Extra: docs
Requires-Dist: sphinx; extra == 'docs'
Provides-Extra: tests
Requires-Dist: pytest; extra == 'tests'
Requires-Dist: pytest-pyramid (>=0.1.1); extra == 'tests'
Requires-Dist: pytest-cov; extra == 'tests'
